outline/__init__.py
outline/_outline.py
outline/_router.py
outline_router-0.0.1.dist-info/LICENSE
outline_router-0.0.1.dist-info/METADATA
outline_router-0.0.1.dist-info/WHEEL
outline_router-0.0.1.dist-info/top_level.txt
outline_router-0.0.1.dist-info/RECORD
