Metadata-Version: 2.1
Name: outline-router
Version: 0.0.1
Summary: Outline Router
Home-page: UNKNOWN
Author: Richard Waschhauser
License: UNKNOWN
Keywords: DXF,PCB
Platform: UNKNOWN
Classifier: Development Status :: 2 - Pre-Alpha
Classifier: Operating System :: POSIX :: Linux
Classifier: Programming Language :: Python :: 3
Classifier: Programming Language :: Python :: 3.5
Classifier: Programming Language :: Python :: 3.6
Classifier: Programming Language :: Python :: 3.7
Classifier: Programming Language :: Python :: 3.8
Classifier: License :: OSI Approved :: MIT License
Requires-Python: >=3.5
Requires-Dist: ezdxf
